{
	"partitions" : [
		{
			"name" : "Top",
			"pins" : [
				{
					"name" : "PC_4[0]",
					"strict" : false
				},
				{
					"name" : "PC_4[1]",
					"strict" : false
				},
				{
					"name" : "PC_4[2]",
					"strict" : false
				},
				{
					"name" : "PC_4[3]",
					"strict" : false
				},
				{
					"name" : "PC_4[4]",
					"strict" : false
				},
				{
					"name" : "PC_4[5]",
					"strict" : false
				},
				{
					"name" : "PC_4[6]",
					"strict" : false
				},
				{
					"name" : "PC_4[7]",
					"strict" : false
				},
				{
					"name" : "PC_4[8]",
					"strict" : false
				},
				{
					"name" : "PC_4[9]",
					"strict" : false
				},
				{
					"name" : "PC_4[10]",
					"strict" : false
				},
				{
					"name" : "PC_4[11]",
					"strict" : false
				},
				{
					"name" : "PC[0]",
					"strict" : false
				},
				{
					"name" : "PC[1]",
					"strict" : false
				},
				{
					"name" : "PC[2]",
					"strict" : false
				},
				{
					"name" : "PC[3]",
					"strict" : false
				},
				{
					"name" : "PC[4]",
					"strict" : false
				},
				{
					"name" : "PC[5]",
					"strict" : false
				},
				{
					"name" : "PC[6]",
					"strict" : false
				},
				{
					"name" : "PC[7]",
					"strict" : false
				},
				{
					"name" : "PC[8]",
					"strict" : false
				},
				{
					"name" : "PC[9]",
					"strict" : false
				},
				{
					"name" : "PC[10]",
					"strict" : false
				},
				{
					"name" : "PC[11]",
					"strict" : false
				}
			]
		}
	]
}